text_actions/__init__.py
text_actions_girvel-0.0.2.dist-info/LICENSE
text_actions_girvel-0.0.2.dist-info/METADATA
text_actions_girvel-0.0.2.dist-info/WHEEL
text_actions_girvel-0.0.2.dist-info/top_level.txt
text_actions_girvel-0.0.2.dist-info/RECORD
