Metadata-Version: 2.1
Name: text-actions-girvel
Version: 0.0.2
Summary: Package for managing UI commands in text package in bash syntax
Home-page: https://github.com/girvel/text_actions
Author: girvel
Author-email: widauka@yandex.ru
License: UNKNOWN
Platform: UNKNOWN
Classifier: Programming Language :: Python :: 3
Classifier: License :: OSI Approved :: MIT License
Classifier: Operating System :: OS Independent
Requires-Python: >=3.6
